{
  "intl-index-home": "Accueil",

  "intl-footer-legals": "Mentions légales",

  "intl-legals-responsible-title": "Responsable du site",
  "intl-legals-responsible-desc": "Ce site a pour responsable Nicolas Burger. Le nom de domaine portraits2passages.eu est la propriété de Nicolas Burger.",
  "intl-legals-development-title": "Développement du site",
  "intl-legals-development-desc": "Le développement du site a été réalisé par Nicolas Burger.",
  "intl-legals-hosting-title": "Hébergement du site",
  "intl-legals-hosting-desc": "Ce site est hébergé avec les services professionnels de la société GitHub.",
  "intl-legals-law-title": "Législation",
  "intl-legals-law-desc": "L'ensemble de ce site relève des législations française et internationale sur le droit d'auteur et la propriété intellectuelle.",
  "intl-legals-responsibility-title": "Limitation de responsabilité",
  "intl-legals-responsibility-desc": "Ce Site comporte des informations mises à disposition par des liens hypertextes vers d’autres sites qui n’ont pas été développés par Nicolas Burger. L’existence d’un lien de ce Site vers un autre site ne constitue pas une validation de ce dernier ou de son contenu. Il appartient à l’internaute d’utiliser ces informations avec discernement et esprit critique et de protéger son ordinateur contre les failles de sécurité. La responsabilité de Portraits 2 Passages et de Nicolas Burger ne saurait être engagée de fait aux informations, opinions et recommandations formulées par des tiers.",

  "intl-404-not-found": "La page demandée est introuvable.",
  "intl-404-go-back-home": "Retour à l'accueil"
}
